adaptfx/__init__.py
adaptfx/_version.py
adaptfx/aft.py
adaptfx/aft_prompt.py
adaptfx/aft_utils.py
adaptfx/constants.py
adaptfx/maths.py
adaptfx/planning.py
adaptfx/radiobiology.py
adaptfx/reinforce.py
adaptfx/reinforce_old.py
adaptfx/visualiser.py
adaptsim/__init__.py
adaptsim/ast.py
adaptsim/constants.py
adaptsim/visualiser.py
adaptsim/visualiser_data.py
adaptfx-0.2.1.dist-info/LICENSE
adaptfx-0.2.1.dist-info/METADATA
adaptfx-0.2.1.dist-info/WHEEL
adaptfx-0.2.1.dist-info/entry_points.txt
adaptfx-0.2.1.dist-info/top_level.txt
adaptfx-0.2.1.dist-info/RECORD
