Metadata-Version: 2.1
Name: adaptfx
Version: 0.2.1
Summary: Package for computing dose fractionation schemes in MR guided Adaptive Radiotherapy
Author-email: Janic Tom Weber <janic.weber@uzh.ch>, Yoel Pérez Haas <yoel.perezhaas@uzh.ch>
License: MIT
Project-URL: source, https://github.com/openAFT/adaptfx
Keywords: fractionation,adaptive radiotherapy,reinforcement-learning
Classifier: License :: OSI Approved :: MIT License
Classifier: Programming Language :: Python :: 3.10
Classifier: Operating System :: OS Independent
Requires-Python: >=3.10
License-File: LICENSE
Requires-Dist: numpy (==1.24.1)
Requires-Dist: scipy (==1.10.0)
Requires-Dist: matplotlib (==3.6.3)
Requires-Dist: pyqt6 (==6.4.0)
Requires-Dist: pandas (==1.5.2)
Requires-Dist: seaborn (==0.12.2)
